[
    {
        "key": "group_70a0000000001",
        "title": "Recipe Fields",
        "fields": [
            {
                "key": "field_70a0000000001",
                "label": "Image",
                "name": "image",
                "aria-label": "",
                "type": "image",
                "instructions": "",
                "required": 1,
                "conditional_logic": 0,
                "wrapper": {"width": "", "class": "", "id": ""},
                "return_format": "url",
                "library": "all",
                "min_width": "",
                "min_height": "",
                "min_size": "",
                "max_width": "",
                "max_height": "",
                "max_size": "",
                "mime_types": "",
                "allow_in_bindings": 0,
                "preview_size": "medium"
            },
            {
                "key": "field_70a0000000002",
                "label": "Description",
                "name": "description",
                "aria-label": "",
                "type": "wysiwyg",
                "instructions": "",
                "required": 0,
                "conditional_logic": 0,
                "wrapper": {"width": "", "class": "", "id": ""},
                "default_value": "",
                "allow_in_bindings": 0,
                "tabs": "all",
                "toolbar": "full",
                "media_upload": 1,
                "delay": 0
            },
            {
                "key": "field_70a0000000003",
                "label": "Prep Time",
                "name": "prep_time",
                "aria-label": "",
                "type": "number",
                "instructions": "",
                "required": 0,
                "conditional_logic": 0,
                "wrapper": {"width": "33", "class": "", "id": ""},
                "default_value": "",
                "min": "",
                "max": "",
                "allow_in_bindings": 0,
                "placeholder": "",
                "step": "",
                "prepend": "",
                "append": "min"
            },
            {
                "key": "field_70a0000000004",
                "label": "Cook Time",
                "name": "cook_time",
                "aria-label": "",
                "type": "number",
                "instructions": "",
                "required": 0,
                "conditional_logic": 0,
                "wrapper": {"width": "33", "class": "", "id": ""},
                "default_value": "",
                "min": "",
                "max": "",
                "allow_in_bindings": 0,
                "placeholder": "",
                "step": "",
                "prepend": "",
                "append": "min"
            },
            {
                "key": "field_70a0000000005",
                "label": "Servings",
                "name": "servings",
                "aria-label": "",
                "type": "number",
                "instructions": "",
                "required": 0,
                "conditional_logic": 0,
                "wrapper": {"width": "33", "class": "", "id": ""},
                "default_value": "",
                "min": "",
                "max": "",
                "allow_in_bindings": 0,
                "placeholder": "",
                "step": "",
                "prepend": "",
                "append": ""
            },
            {
                "key": "field_70a0000000006",
                "label": "Difficulty",
                "name": "difficulty",
                "aria-label": "",
                "type": "select",
                "instructions": "",
                "required": 0,
                "conditional_logic": 0,
                "wrapper": {"width": "33", "class": "", "id": ""},
                "choices": {"easy": "Easy", "medium": "Medium", "hard": "Hard"},
                "default_value": false,
                "return_format": "value",
                "multiple": 0,
                "allow_null": 1,
                "allow_in_bindings": 0,
                "ui": 0,
                "ajax": 0,
                "placeholder": "",
                "create_options": 0,
                "save_options": 0
            },
            {
                "key": "field_70a0000000007",
                "label": "Cuisine",
                "name": "cuisine",
                "aria-label": "",
                "type": "taxonomy",
                "instructions": "",
                "required": 0,
                "conditional_logic": 0,
                "wrapper": {"width": "", "class": "", "id": ""},
                "taxonomy": "cuisine",
                "add_term": 1,
                "save_terms": 1,
                "load_terms": 0,
                "return_format": "id",
                "field_type": "select",
                "allow_null": 1,
                "allow_in_bindings": 0,
                "bidirectional": 0,
                "multiple": 0,
                "bidirectional_target": []
            },
            {
                "key": "field_70a0000000008",
                "label": "Course",
                "name": "course",
                "aria-label": "",
                "type": "taxonomy",
                "instructions": "",
                "required": 0,
                "conditional_logic": 0,
                "wrapper": {"width": "", "class": "", "id": ""},
                "taxonomy": "course",
                "add_term": 1,
                "save_terms": 1,
                "load_terms": 0,
                "return_format": "id",
                "field_type": "select",
                "allow_null": 1,
                "allow_in_bindings": 0,
                "bidirectional": 0,
                "multiple": 0,
                "bidirectional_target": []
            },
            {
                "key": "field_70a0000000009",
                "label": "Diet",
                "name": "diet",
                "aria-label": "",
                "type": "taxonomy",
                "instructions": "",
                "required": 0,
                "conditional_logic": 0,
                "wrapper": {"width": "", "class": "", "id": ""},
                "taxonomy": "diet",
                "add_term": 1,
                "save_terms": 1,
                "load_terms": 0,
                "return_format": "id",
                "field_type": "select",
                "allow_null": 1,
                "allow_in_bindings": 0,
                "bidirectional": 0,
                "multiple": 0,
                "bidirectional_target": []
            },
            {
                "key": "field_70a000000000a",
                "label": "Chefs",
                "name": "chefs",
                "aria-label": "",
                "type": "relationship",
                "instructions": "",
                "required": 0,
                "conditional_logic": 0,
                "wrapper": {"width": "", "class": "", "id": ""},
                "post_type": ["chef"],
                "post_status": ["publish"],
                "taxonomy": "",
                "filters": ["search", "post_type"],
                "return_format": "object",
                "min": "",
                "max": "",
                "allow_in_bindings": 0,
                "elements": "",
                "bidirectional": 1,
                "bidirectional_target": ["field_70a000000000a"]
            },
            {
                "key": "field_70a000000000b",
                "label": "Cookbooks",
                "name": "cookbooks",
                "aria-label": "",
                "type": "relationship",
                "instructions": "",
                "required": 0,
                "conditional_logic": 0,
                "wrapper": {"width": "", "class": "", "id": ""},
                "post_type": ["cookbook"],
                "post_status": ["publish"],
                "taxonomy": "",
                "filters": ["search", "post_type"],
                "return_format": "object",
                "min": "",
                "max": "",
                "allow_in_bindings": 0,
                "elements": "",
                "bidirectional": 1,
                "bidirectional_target": ["field_70a000000000b"]
            },
            {
                "key": "field_70a000000000c",
                "label": "Ingredients",
                "name": "ingredients",
                "aria-label": "",
                "type": "repeater",
                "instructions": "",
                "required": 0,
                "conditional_logic": 0,
                "wrapper": {"width": "", "class": "", "id": ""},
                "layout": "table",
                "pagination": 0,
                "min": 0,
                "max": 0,
                "collapsed": "",
                "button_label": "Add Row",
                "rows_per_page": 20,
                "sub_fields": [
                    {
                        "key": "field_70a000000000d",
                        "label": "Ingredient",
                        "name": "ingredient",
                        "aria-label": "",
                        "type": "text",
                        "instructions": "",
                        "required": 0,
                        "conditional_logic": 0,
                        "wrapper": {"width": "", "class": "", "id": ""},
                        "default_value": "",
                        "maxlength": "",
                        "allow_in_bindings": 0,
                        "placeholder": "",
                        "prepend": "",
                        "append": "",
                        "parent_repeater": "field_70a000000000c"
                    },
                    {
                        "key": "field_70a000000000e",
                        "label": "Amount",
                        "name": "amount",
                        "aria-label": "",
                        "type": "text",
                        "instructions": "",
                        "required": 0,
                        "conditional_logic": 0,
                        "wrapper": {"width": "", "class": "", "id": ""},
                        "default_value": "",
                        "maxlength": "",
                        "allow_in_bindings": 0,
                        "placeholder": "",
                        "prepend": "",
                        "append": "",
                        "parent_repeater": "field_70a000000000c"
                    },
                    {
                        "key": "field_70a000000000f",
                        "label": "Unit",
                        "name": "unit",
                        "aria-label": "",
                        "type": "select",
                        "instructions": "",
                        "required": 0,
                        "conditional_logic": 0,
                        "wrapper": {"width": "", "class": "", "id": ""},
                        "choices": {
                            "g": "g",
                            "kg": "kg",
                            "ml": "ml",
                            "l": "l",
                            "tsp": "tsp",
                            "tbsp": "tbsp",
                            "cup": "cup",
                            "piece": "piece",
                            "pinch": "pinch"
                        },
                        "default_value": false,
                        "return_format": "value",
                        "multiple": 0,
                        "allow_null": 1,
                        "allow_in_bindings": 0,
                        "ui": 0,
                        "ajax": 0,
                        "placeholder": "",
                        "create_options": 0,
                        "save_options": 0,
                        "parent_repeater": "field_70a000000000c"
                    }
                ]
            },
            {
                "key": "field_70a0000000010",
                "label": "Instructions",
                "name": "instructions",
                "aria-label": "",
                "type": "repeater",
                "instructions": "",
                "required": 0,
                "conditional_logic": 0,
                "wrapper": {"width": "", "class": "", "id": ""},
                "layout": "table",
                "pagination": 0,
                "min": 0,
                "max": 0,
                "collapsed": "",
                "button_label": "Add Row",
                "rows_per_page": 20,
                "sub_fields": [
                    {
                        "key": "field_70a0000000011",
                        "label": "Step",
                        "name": "step",
                        "aria-label": "",
                        "type": "number",
                        "instructions": "",
                        "required": 0,
                        "conditional_logic": 0,
                        "wrapper": {"width": "15", "class": "", "id": ""},
                        "default_value": "",
                        "min": "",
                        "max": "",
                        "allow_in_bindings": 0,
                        "placeholder": "",
                        "step": "",
                        "prepend": "",
                        "append": "",
                        "parent_repeater": "field_70a0000000010"
                    },
                    {
                        "key": "field_70a0000000012",
                        "label": "Instruction Text",
                        "name": "instruction_text",
                        "aria-label": "",
                        "type": "textarea",
                        "instructions": "",
                        "required": 0,
                        "conditional_logic": 0,
                        "wrapper": {"width": "", "class": "", "id": ""},
                        "default_value": "",
                        "maxlength": "",
                        "allow_in_bindings": 0,
                        "rows": "",
                        "placeholder": "",
                        "new_lines": "",
                        "parent_repeater": "field_70a0000000010"
                    },
                    {
                        "key": "field_70a0000000013",
                        "label": "Step Image",
                        "name": "step_image",
                        "aria-label": "",
                        "type": "image",
                        "instructions": "",
                        "required": 0,
                        "conditional_logic": 0,
                        "wrapper": {"width": "", "class": "", "id": ""},
                        "return_format": "url",
                        "library": "all",
                        "min_width": "",
                        "min_height": "",
                        "min_size": "",
                        "max_width": "",
                        "max_height": "",
                        "max_size": "",
                        "mime_types": "",
                        "allow_in_bindings": 0,
                        "preview_size": "medium",
                        "parent_repeater": "field_70a0000000010"
                    }
                ]
            },
            {
                "key": "field_70a0000000014",
                "label": "Nutrition",
                "name": "nutrition",
                "aria-label": "",
                "type": "repeater",
                "instructions": "",
                "required": 0,
                "conditional_logic": 0,
                "wrapper": {"width": "", "class": "", "id": ""},
                "layout": "table",
                "pagination": 0,
                "min": 0,
                "max": 0,
                "collapsed": "",
                "button_label": "Add Row",
                "rows_per_page": 20,
                "sub_fields": [
                    {
                        "key": "field_70a0000000015",
                        "label": "Nutrient",
                        "name": "nutrient",
                        "aria-label": "",
                        "type": "text",
                        "instructions": "",
                        "required": 0,
                        "conditional_logic": 0,
                        "wrapper": {"width": "", "class": "", "id": ""},
                        "default_value": "",
                        "maxlength": "",
                        "allow_in_bindings": 0,
                        "placeholder": "",
                        "prepend": "",
                        "append": "",
                        "parent_repeater": "field_70a0000000014"
                    },
                    {
                        "key": "field_70a0000000016",
                        "label": "Nutrient Value",
                        "name": "nutrient_value",
                        "aria-label": "",
                        "type": "text",
                        "instructions": "",
                        "required": 0,
                        "conditional_logic": 0,
                        "wrapper": {"width": "", "class": "", "id": ""},
                        "default_value": "",
                        "maxlength": "",
                        "allow_in_bindings": 0,
                        "placeholder": "",
                        "prepend": "",
                        "append": "",
                        "parent_repeater": "field_70a0000000014"
                    }
                ]
            }
        ],
        "location": [[{"param": "post_type", "operator": "==", "value": "recipe"}]],
        "menu_order": 0,
        "position": "normal",
        "style": "default",
        "label_placement": "top",
        "instruction_placement": "label",
        "hide_on_screen": "",
        "active": true,
        "description": "",
        "show_in_rest": 0,
        "display_title": ""
    },
    {
        "key": "group_70a0000000002",
        "title": "Chef Fields",
        "fields": [
            {
                "key": "field_70a0000000017",
                "label": "First Name",
                "name": "first_name",
                "aria-label": "",
                "type": "text",
                "instructions": "",
                "required": 1,
                "conditional_logic": 0,
                "wrapper": {"width": "33", "class": "", "id": ""},
                "default_value": "",
                "maxlength": "",
                "allow_in_bindings": 0,
                "placeholder": "",
                "prepend": "",
                "append": ""
            },
            {
                "key": "field_70a0000000018",
                "label": "Last Name",
                "name": "last_name",
                "aria-label": "",
                "type": "text",
                "instructions": "",
                "required": 1,
                "conditional_logic": 0,
                "wrapper": {"width": "33", "class": "", "id": ""},
                "default_value": "",
                "maxlength": "",
                "allow_in_bindings": 0,
                "placeholder": "",
                "prepend": "",
                "append": ""
            },
            {
                "key": "field_70a0000000019",
                "label": "Bio",
                "name": "bio",
                "aria-label": "",
                "type": "wysiwyg",
                "instructions": "",
                "required": 0,
                "conditional_logic": 0,
                "wrapper": {"width": "", "class": "", "id": ""},
                "default_value": "",
                "allow_in_bindings": 0,
                "tabs": "all",
                "toolbar": "full",
                "media_upload": 1,
                "delay": 0
            },
            {
                "key": "field_70a000000001a",
                "label": "Photo",
                "name": "photo",
                "aria-label": "",
                "type": "image",
                "instructions": "",
                "required": 0,
                "conditional_logic": 0,
                "wrapper": {"width": "", "class": "", "id": ""},
                "return_format": "url",
                "library": "all",
                "min_width": "",
                "min_height": "",
                "min_size": "",
                "max_width": "",
                "max_height": "",
                "max_size": "",
                "mime_types": "",
                "allow_in_bindings": 0,
                "preview_size": "medium"
            },
            {
                "key": "field_70a000000001b",
                "label": "Website",
                "name": "website",
                "aria-label": "",
                "type": "url",
                "instructions": "",
                "required": 0,
                "conditional_logic": 0,
                "wrapper": {"width": "", "class": "", "id": ""},
                "default_value": "",
                "allow_in_bindings": 0,
                "placeholder": ""
            },
            {
                "key": "field_70a000000001c",
                "label": "Recipes",
                "name": "recipes",
                "aria-label": "",
                "type": "relationship",
                "instructions": "",
                "required": 0,
                "conditional_logic": 0,
                "wrapper": {"width": "", "class": "", "id": ""},
                "post_type": ["recipe"],
                "post_status": ["publish"],
                "taxonomy": "",
                "filters": ["search", "post_type"],
                "return_format": "object",
                "min": "",
                "max": "",
                "allow_in_bindings": 0,
                "elements": "",
                "bidirectional": 1,
                "bidirectional_target": ["field_70a000000001c"]
            }
        ],
        "location": [[{"param": "post_type", "operator": "==", "value": "chef"}]],
        "menu_order": 0,
        "position": "normal",
        "style": "default",
        "label_placement": "top",
        "instruction_placement": "label",
        "hide_on_screen": "",
        "active": true,
        "description": "",
        "show_in_rest": 0,
        "display_title": ""
    },
    {
        "key": "group_70a0000000003",
        "title": "Cookbook Fields",
        "fields": [
            {
                "key": "field_70a000000001d",
                "label": "Cover Image",
                "name": "cover_image",
                "aria-label": "",
                "type": "image",
                "instructions": "",
                "required": 0,
                "conditional_logic": 0,
                "wrapper": {"width": "", "class": "", "id": ""},
                "return_format": "url",
                "library": "all",
                "min_width": "",
                "min_height": "",
                "min_size": "",
                "max_width": "",
                "max_height": "",
                "max_size": "",
                "mime_types": "",
                "allow_in_bindings": 0,
                "preview_size": "medium"
            },
            {
                "key": "field_70a000000001e",
                "label": "Publisher",
                "name": "publisher",
                "aria-label": "",
                "type": "text",
                "instructions": "",
                "required": 0,
                "conditional_logic": 0,
                "wrapper": {"width": "33", "class": "", "id": ""},
                "default_value": "",
                "maxlength": "",
                "allow_in_bindings": 0,
                "placeholder": "",
                "prepend": "",
                "append": ""
            },
            {
                "key": "field_70a000000001f",
                "label": "Year",
                "name": "year",
                "aria-label": "",
                "type": "number",
                "instructions": "",
                "required": 0,
                "conditional_logic": 0,
                "wrapper": {"width": "33", "class": "", "id": ""},
                "default_value": "",
                "min": "",
                "max": "",
                "allow_in_bindings": 0,
                "placeholder": "",
                "step": "",
                "prepend": "",
                "append": ""
            },
            {
                "key": "field_70a0000000020",
                "label": "ISBN",
                "name": "isbn",
                "aria-label": "",
                "type": "text",
                "instructions": "",
                "required": 0,
                "conditional_logic": 0,
                "wrapper": {"width": "33", "class": "", "id": ""},
                "default_value": "",
                "maxlength": "",
                "allow_in_bindings": 0,
                "placeholder": "",
                "prepend": "",
                "append": ""
            },
            {
                "key": "field_70a0000000021",
                "label": "Description",
                "name": "description",
                "aria-label": "",
                "type": "textarea",
                "instructions": "",
                "required": 0,
                "conditional_logic": 0,
                "wrapper": {"width": "", "class": "", "id": ""},
                "default_value": "",
                "maxlength": "",
                "allow_in_bindings": 0,
                "rows": "",
                "placeholder": "",
                "new_lines": ""
            },
            {
                "key": "field_70a0000000022",
                "label": "Recipes",
                "name": "recipes",
                "aria-label": "",
                "type": "relationship",
                "instructions": "",
                "required": 0,
                "conditional_logic": 0,
                "wrapper": {"width": "", "class": "", "id": ""},
                "post_type": ["recipe"],
                "post_status": ["publish"],
                "taxonomy": "",
                "filters": ["search", "post_type"],
                "return_format": "object",
                "min": "",
                "max": "",
                "allow_in_bindings": 0,
                "elements": "",
                "bidirectional": 1,
                "bidirectional_target": ["field_70a0000000022"]
            }
        ],
        "location": [[{"param": "post_type", "operator": "==", "value": "cookbook"}]],
        "menu_order": 0,
        "position": "normal",
        "style": "default",
        "label_placement": "top",
        "instruction_placement": "label",
        "hide_on_screen": "",
        "active": true,
        "description": "",
        "show_in_rest": 0,
        "display_title": ""
    },
    {
        "key": "taxonomy_70a0000000001",
        "title": "Cuisines",
        "menu_order": 0,
        "active": true,
        "taxonomy": "cuisine",
        "object_type": ["recipe"],
        "advanced_configuration": 0,
        "import_source": "",
        "import_date": "",
        "labels": {
            "name": "Cuisines",
            "singular_name": "Cuisine",
            "menu_name": "Cuisines",
            "all_items": "All Cuisines",
            "edit_item": "Edit Cuisine",
            "view_item": "View Cuisine",
            "update_item": "Update Cuisine",
            "add_new_item": "Add New Cuisine",
            "new_item_name": "New Cuisine Name",
            "search_items": "Search Cuisines",
            "popular_items": "Popular Cuisines",
            "separate_items_with_commas": "Separate cuisines with commas",
            "add_or_remove_items": "Add or remove cuisines",
            "choose_from_most_used": "Choose from the most used cuisines",
            "most_used": "",
            "not_found": "No cuisines found",
            "no_terms": "No cuisines",
            "name_field_description": "",
            "slug_field_description": "",
            "desc_field_description": "",
            "items_list_navigation": "Cuisines list navigation",
            "items_list": "Cuisines list",
            "back_to_items": "\u2190 Go to cuisines",
            "item_link": "Cuisine Link",
            "item_link_description": "A link to a cuisine"
        },
        "description": "",
        "capabilities": {
            "manage_terms": "manage_categories",
            "edit_terms": "manage_categories",
            "delete_terms": "manage_categories",
            "assign_terms": "edit_posts"
        },
        "public": 1,
        "publicly_queryable": 1,
        "hierarchical": 0,
        "show_ui": 1,
        "show_in_menu": 1,
        "show_in_nav_menus": 1,
        "show_in_rest": 1,
        "rest_base": "",
        "rest_namespace": "wp\/v2",
        "rest_controller_class": "WP_REST_Terms_Controller",
        "show_tagcloud": 1,
        "show_in_quick_edit": 1,
        "show_admin_column": 0,
        "rewrite": {
            "permalink_rewrite": "taxonomy_key",
            "with_front": "1",
            "rewrite_hierarchical": "0"
        },
        "query_var": "post_type_key",
        "query_var_name": "",
        "default_term": {"default_term_enabled": "0"},
        "sort": 0,
        "meta_box": "default",
        "meta_box_cb": "",
        "meta_box_sanitize_cb": ""
    },
    {
        "key": "taxonomy_70a0000000002",
        "title": "Courses",
        "menu_order": 0,
        "active": true,
        "taxonomy": "course",
        "object_type": ["recipe"],
        "advanced_configuration": 0,
        "import_source": "",
        "import_date": "",
        "labels": {
            "name": "Courses",
            "singular_name": "Course",
            "menu_name": "Courses",
            "all_items": "All Courses",
            "edit_item": "Edit Course",
            "view_item": "View Course",
            "update_item": "Update Course",
            "add_new_item": "Add New Course",
            "new_item_name": "New Course Name",
            "search_items": "Search Courses",
            "popular_items": "Popular Courses",
            "separate_items_with_commas": "Separate courses with commas",
            "add_or_remove_items": "Add or remove courses",
            "choose_from_most_used": "Choose from the most used courses",
            "most_used": "",
            "not_found": "No courses found",
            "no_terms": "No courses",
            "name_field_description": "",
            "slug_field_description": "",
            "desc_field_description": "",
            "items_list_navigation": "Courses list navigation",
            "items_list": "Courses list",
            "back_to_items": "\u2190 Go to courses",
            "item_link": "Course Link",
            "item_link_description": "A link to a course"
        },
        "description": "",
        "capabilities": {
            "manage_terms": "manage_categories",
            "edit_terms": "manage_categories",
            "delete_terms": "manage_categories",
            "assign_terms": "edit_posts"
        },
        "public": 1,
        "publicly_queryable": 1,
        "hierarchical": 0,
        "show_ui": 1,
        "show_in_menu": 1,
        "show_in_nav_menus": 1,
        "show_in_rest": 1,
        "rest_base": "",
        "rest_namespace": "wp\/v2",
        "rest_controller_class": "WP_REST_Terms_Controller",
        "show_tagcloud": 1,
        "show_in_quick_edit": 1,
        "show_admin_column": 0,
        "rewrite": {
            "permalink_rewrite": "taxonomy_key",
            "with_front": "1",
            "rewrite_hierarchical": "0"
        },
        "query_var": "post_type_key",
        "query_var_name": "",
        "default_term": {"default_term_enabled": "0"},
        "sort": 0,
        "meta_box": "default",
        "meta_box_cb": "",
        "meta_box_sanitize_cb": ""
    },
    {
        "key": "taxonomy_70a0000000003",
        "title": "Diets",
        "menu_order": 0,
        "active": true,
        "taxonomy": "diet",
        "object_type": ["recipe"],
        "advanced_configuration": 0,
        "import_source": "",
        "import_date": "",
        "labels": {
            "name": "Diets",
            "singular_name": "Diet",
            "menu_name": "Diets",
            "all_items": "All Diets",
            "edit_item": "Edit Diet",
            "view_item": "View Diet",
            "update_item": "Update Diet",
            "add_new_item": "Add New Diet",
            "new_item_name": "New Diet Name",
            "search_items": "Search Diets",
            "popular_items": "Popular Diets",
            "separate_items_with_commas": "Separate diets with commas",
            "add_or_remove_items": "Add or remove diets",
            "choose_from_most_used": "Choose from the most used diets",
            "most_used": "",
            "not_found": "No diets found",
            "no_terms": "No diets",
            "name_field_description": "",
            "slug_field_description": "",
            "desc_field_description": "",
            "items_list_navigation": "Diets list navigation",
            "items_list": "Diets list",
            "back_to_items": "\u2190 Go to diets",
            "item_link": "Diet Link",
            "item_link_description": "A link to a diet"
        },
        "description": "",
        "capabilities": {
            "manage_terms": "manage_categories",
            "edit_terms": "manage_categories",
            "delete_terms": "manage_categories",
            "assign_terms": "edit_posts"
        },
        "public": 1,
        "publicly_queryable": 1,
        "hierarchical": 0,
        "show_ui": 1,
        "show_in_menu": 1,
        "show_in_nav_menus": 1,
        "show_in_rest": 1,
        "rest_base": "",
        "rest_namespace": "wp\/v2",
        "rest_controller_class": "WP_REST_Terms_Controller",
        "show_tagcloud": 1,
        "show_in_quick_edit": 1,
        "show_admin_column": 0,
        "rewrite": {
            "permalink_rewrite": "taxonomy_key",
            "with_front": "1",
            "rewrite_hierarchical": "0"
        },
        "query_var": "post_type_key",
        "query_var_name": "",
        "default_term": {"default_term_enabled": "0"},
        "sort": 0,
        "meta_box": "default",
        "meta_box_cb": "",
        "meta_box_sanitize_cb": ""
    },
    {
        "key": "post_type_70a0000000001",
        "title": "Recipes",
        "menu_order": 0,
        "active": true,
        "post_type": "recipe",
        "advanced_configuration": true,
        "import_source": "",
        "import_date": "",
        "labels": {
            "name": "Recipes",
            "singular_name": "Recipe",
            "menu_name": "Recipes",
            "all_items": "All Recipes",
            "edit_item": "Edit Recipe",
            "view_item": "View Recipe",
            "view_items": "View Recipes",
            "add_new_item": "Add New Recipe",
            "add_new": "Add New Recipe",
            "new_item": "New Recipe",
            "parent_item_colon": "Parent Recipe:",
            "search_items": "Search Recipes",
            "not_found": "No recipes found",
            "not_found_in_trash": "No recipes found in Trash",
            "archives": "Recipe Archives",
            "attributes": "Recipe Attributes",
            "featured_image": "",
            "set_featured_image": "",
            "remove_featured_image": "",
            "use_featured_image": "",
            "insert_into_item": "Insert into recipe",
            "uploaded_to_this_item": "Uploaded to this recipe",
            "filter_items_list": "Filter recipes list",
            "filter_by_date": "Filter recipes by date",
            "items_list_navigation": "Recipes list navigation",
            "items_list": "Recipes list",
            "item_published": "Recipe published.",
            "item_published_privately": "Recipe published privately.",
            "item_reverted_to_draft": "Recipe reverted to draft.",
            "item_scheduled": "Recipe scheduled.",
            "item_updated": "Recipe updated.",
            "item_link": "Recipe Link",
            "item_link_description": "A link to a recipe."
        },
        "description": "",
        "public": true,
        "hierarchical": false,
        "exclude_from_search": false,
        "publicly_queryable": true,
        "show_ui": true,
        "show_in_menu": true,
        "admin_menu_parent": "",
        "show_in_admin_bar": true,
        "show_in_nav_menus": true,
        "show_in_rest": true,
        "rest_base": "",
        "rest_namespace": "wp\/v2",
        "rest_controller_class": "WP_REST_Posts_Controller",
        "menu_position": "",
        "menu_icon": {"type": "dashicons", "value": "dashicons-carrot"},
        "rename_capabilities": false,
        "singular_capability_name": "post",
        "plural_capability_name": "posts",
        "supports": ["title", "thumbnail", "custom-fields"],
        "taxonomies": "",
        "has_archive": false,
        "has_archive_slug": "",
        "rewrite": {
            "permalink_rewrite": "post_type_key",
            "with_front": "1",
            "feeds": "0",
            "pages": "1"
        },
        "query_var": "post_type_key",
        "query_var_name": "",
        "can_export": true,
        "delete_with_user": false,
        "register_meta_box_cb": "",
        "enter_title_here": ""
    },
    {
        "key": "post_type_70a0000000002",
        "title": "Chefs",
        "menu_order": 0,
        "active": true,
        "post_type": "chef",
        "advanced_configuration": true,
        "import_source": "",
        "import_date": "",
        "labels": {
            "name": "Chefs",
            "singular_name": "Chef",
            "menu_name": "Chefs",
            "all_items": "All Chefs",
            "edit_item": "Edit Chef",
            "view_item": "View Chef",
            "view_items": "View Chefs",
            "add_new_item": "Add New Chef",
            "add_new": "Add New Chef",
            "new_item": "New Chef",
            "parent_item_colon": "Parent Chef:",
            "search_items": "Search Chefs",
            "not_found": "No chefs found",
            "not_found_in_trash": "No chefs found in Trash",
            "archives": "Chef Archives",
            "attributes": "Chef Attributes",
            "featured_image": "",
            "set_featured_image": "",
            "remove_featured_image": "",
            "use_featured_image": "",
            "insert_into_item": "Insert into chef",
            "uploaded_to_this_item": "Uploaded to this chef",
            "filter_items_list": "Filter chefs list",
            "filter_by_date": "Filter chefs by date",
            "items_list_navigation": "Chefs list navigation",
            "items_list": "Chefs list",
            "item_published": "Chef published.",
            "item_published_privately": "Chef published privately.",
            "item_reverted_to_draft": "Chef reverted to draft.",
            "item_scheduled": "Chef scheduled.",
            "item_updated": "Chef updated.",
            "item_link": "Chef Link",
            "item_link_description": "A link to a chef."
        },
        "description": "",
        "public": true,
        "hierarchical": false,
        "exclude_from_search": false,
        "publicly_queryable": true,
        "show_ui": true,
        "show_in_menu": true,
        "admin_menu_parent": "",
        "show_in_admin_bar": true,
        "show_in_nav_menus": true,
        "show_in_rest": true,
        "rest_base": "",
        "rest_namespace": "wp\/v2",
        "rest_controller_class": "WP_REST_Posts_Controller",
        "menu_position": "",
        "menu_icon": {"type": "dashicons", "value": "dashicons-admin-users"},
        "rename_capabilities": false,
        "singular_capability_name": "post",
        "plural_capability_name": "posts",
        "supports": ["title", "thumbnail", "custom-fields"],
        "taxonomies": "",
        "has_archive": false,
        "has_archive_slug": "",
        "rewrite": {
            "permalink_rewrite": "post_type_key",
            "with_front": "1",
            "feeds": "0",
            "pages": "1"
        },
        "query_var": "post_type_key",
        "query_var_name": "",
        "can_export": true,
        "delete_with_user": false,
        "register_meta_box_cb": "",
        "enter_title_here": ""
    },
    {
        "key": "post_type_70a0000000003",
        "title": "Cookbooks",
        "menu_order": 0,
        "active": true,
        "post_type": "cookbook",
        "advanced_configuration": true,
        "import_source": "",
        "import_date": "",
        "labels": {
            "name": "Cookbooks",
            "singular_name": "Cookbook",
            "menu_name": "Cookbooks",
            "all_items": "All Cookbooks",
            "edit_item": "Edit Cookbook",
            "view_item": "View Cookbook",
            "view_items": "View Cookbooks",
            "add_new_item": "Add New Cookbook",
            "add_new": "Add New Cookbook",
            "new_item": "New Cookbook",
            "parent_item_colon": "Parent Cookbook:",
            "search_items": "Search Cookbooks",
            "not_found": "No cookbooks found",
            "not_found_in_trash": "No cookbooks found in Trash",
            "archives": "Cookbook Archives",
            "attributes": "Cookbook Attributes",
            "featured_image": "",
            "set_featured_image": "",
            "remove_featured_image": "",
            "use_featured_image": "",
            "insert_into_item": "Insert into cookbook",
            "uploaded_to_this_item": "Uploaded to this cookbook",
            "filter_items_list": "Filter cookbooks list",
            "filter_by_date": "Filter cookbooks by date",
            "items_list_navigation": "Cookbooks list navigation",
            "items_list": "Cookbooks list",
            "item_published": "Cookbook published.",
            "item_published_privately": "Cookbook published privately.",
            "item_reverted_to_draft": "Cookbook reverted to draft.",
            "item_scheduled": "Cookbook scheduled.",
            "item_updated": "Cookbook updated.",
            "item_link": "Cookbook Link",
            "item_link_description": "A link to a cookbook."
        },
        "description": "",
        "public": true,
        "hierarchical": false,
        "exclude_from_search": false,
        "publicly_queryable": true,
        "show_ui": true,
        "show_in_menu": true,
        "admin_menu_parent": "",
        "show_in_admin_bar": true,
        "show_in_nav_menus": true,
        "show_in_rest": true,
        "rest_base": "",
        "rest_namespace": "wp\/v2",
        "rest_controller_class": "WP_REST_Posts_Controller",
        "menu_position": "",
        "menu_icon": {"type": "dashicons", "value": "dashicons-book"},
        "rename_capabilities": false,
        "singular_capability_name": "post",
        "plural_capability_name": "posts",
        "supports": ["title", "thumbnail", "custom-fields"],
        "taxonomies": "",
        "has_archive": false,
        "has_archive_slug": "",
        "rewrite": {
            "permalink_rewrite": "post_type_key",
            "with_front": "1",
            "feeds": "0",
            "pages": "1"
        },
        "query_var": "post_type_key",
        "query_var_name": "",
        "can_export": true,
        "delete_with_user": false,
        "register_meta_box_cb": "",
        "enter_title_here": ""
    }
]
